MonashUE1013/MonashUE1013.py
MonashUE1013/__init__.py
MonashUE1013/ProjectResources/ProjectResources.py
MonashUE1013/ProjectResources/__init__.py
MonashUE1013-1.10.3.dist-info/METADATA
MonashUE1013-1.10.3.dist-info/WHEEL
MonashUE1013-1.10.3.dist-info/top_level.txt
MonashUE1013-1.10.3.dist-info/RECORD
