Metadata-Version: 2.1
Name: MonashUE1013
Version: 1.10.3
Summary: Package to support student projects for ENG1013 at Monash University
Author: Monash University
Author-email: eng1013.clayton-x@monash.edu
Classifier: Programming Language :: Python :: 3
Classifier: Operating System :: OS Independent
Classifier: License :: OSI Approved :: GNU Affero General Public License v3 or later (AGPLv3+)
Requires-Python: >=3.8
License-File: license.txt
Requires-Dist: pymata4
